gigman/__init__.py
gigman/__main__.py
gigman/app.py
gigman/display.py
gigman/gitignore.py
gigman/keyboard.py
gigman/logger.py
gigman/manager.py
gigman/parse.py
gigman/provider.py
gigman/section.py
gigman/template.py
gigman/ui.py
gigman/data/AL.gitignore
gigman/data/Actionscript.gitignore
gigman/data/Ada.gitignore
gigman/data/Agda.gitignore
gigman/data/Android.gitignore
gigman/data/AppEngine.gitignore
gigman/data/AppceleratorTitanium.gitignore
gigman/data/ArchLinuxPackages.gitignore
gigman/data/Autotools.gitignore
gigman/data/C++.gitignore
gigman/data/C.gitignore
gigman/data/CFWheels.gitignore
gigman/data/CMake.gitignore
gigman/data/CUDA.gitignore
gigman/data/CakePHP.gitignore
gigman/data/ChefCookbook.gitignore
gigman/data/Clojure.gitignore
gigman/data/CodeIgniter.gitignore
gigman/data/CommonLisp.gitignore
gigman/data/Composer.gitignore
gigman/data/Concrete5.gitignore
gigman/data/Coq.gitignore
gigman/data/CraftCMS.gitignore
gigman/data/D.gitignore
gigman/data/DM.gitignore
gigman/data/Dart.gitignore
gigman/data/Delphi.gitignore
gigman/data/Drupal.gitignore
gigman/data/EPiServer.gitignore
gigman/data/Eagle.gitignore
gigman/data/Elisp.gitignore
gigman/data/Elixir.gitignore
gigman/data/Elm.gitignore
gigman/data/Erlang.gitignore
gigman/data/ExpressionEngine.gitignore
gigman/data/ExtJs.gitignore
gigman/data/Fancy.gitignore
gigman/data/Finale.gitignore
gigman/data/FlaxEngine.gitignore
gigman/data/ForceDotCom.gitignore
gigman/data/Fortran.gitignore
gigman/data/FuelPHP.gitignore
gigman/data/GWT.gitignore
gigman/data/Gcov.gitignore
gigman/data/GitBook.gitignore
gigman/data/Go.gitignore
gigman/data/Godot.gitignore
gigman/data/Gradle.gitignore
gigman/data/Grails.gitignore
gigman/data/Haskell.gitignore
gigman/data/IGORPro.gitignore
gigman/data/Idris.gitignore
gigman/data/JBoss.gitignore
gigman/data/JENKINS_HOME.gitignore
gigman/data/Java.gitignore
gigman/data/Jekyll.gitignore
gigman/data/Joomla.gitignore
gigman/data/Julia.gitignore
gigman/data/KiCad.gitignore
gigman-0.0.9.dist-info/LICENSE
gigman-0.0.9.dist-info/METADATA
gigman-0.0.9.dist-info/WHEEL
gigman-0.0.9.dist-info/entry_points.txt
gigman-0.0.9.dist-info/top_level.txt
gigman-0.0.9.dist-info/RECORD
