Metadata-Version: 2.1
Name: gigman
Version: 0.0.9
Summary: a no-nonsense gitignore manager
Author-email: Rex Garland <rex@rexgarland.dev>
License: GNU GENERAL PUBLIC LICENSE
Project-URL: Source, https://git.sr.ht/~rexgarland/gigman
Classifier: Programming Language :: Python :: 3
Classifier: License :: OSI Approved :: GNU General Public License v3 (GPLv3)
Classifier: Operating System :: OS Independent
Requires-Python: >=3.7
License-File: LICENSE
Requires-Dist: importlib-resources (==5.9.0)
